opendiamond/__init__.py
opendiamond/attributes.py
opendiamond/blobcache.py
opendiamond/bundle.py
opendiamond/bundle.xsd
opendiamond/bundle.xslt
opendiamond/config.py
opendiamond/helpers.py
opendiamond/protocol.py
opendiamond/rpc.py
opendiamond/scope.py
opendiamond/xdr.py
opendiamond/blaster/__init__.py
opendiamond/blaster/__main__.py
opendiamond/blaster/cache.py
opendiamond/blaster/handlers.py
opendiamond/blaster/json.py
opendiamond/blaster/rpc.py
opendiamond/blaster/search.py
opendiamond/blaster/static/json-blaster-autopause.js
opendiamond/blaster/static/json-blaster.js
opendiamond/blaster/static/sockjs.js
opendiamond/blaster/static/testui/jquery.js
opendiamond/blaster/static/testui/spinner.gif
opendiamond/blaster/static/testui/unknown.png
opendiamond/blaster/templates/testui/result.html
opendiamond/blaster/templates/testui/results.html
opendiamond/blaster/templates/testui/search.html
opendiamond/client/__init__.py
opendiamond/client/rpc.py
opendiamond/client/search.py
opendiamond/client/util.py
opendiamond/dataretriever/__init__.py
opendiamond/dataretriever/__main__.py
opendiamond/dataretriever/augment_store.py
opendiamond/dataretriever/carbon_v1_store.py
opendiamond/dataretriever/diamond_store.py
opendiamond/dataretriever/gigapan_store.py
opendiamond/dataretriever/mixer_store.py
opendiamond/dataretriever/proxy_store.py
opendiamond/dataretriever/pyramid.py
opendiamond/dataretriever/test_store.py
opendiamond/dataretriever/test_utils.py
opendiamond/dataretriever/util.py
opendiamond/dataretriever/video_store.py
opendiamond/dataretriever/yfcc100m_mysql_store.py
opendiamond/dataretriever/yfcc100m_simple_store.py
opendiamond/dataretriever/yfcc100m_vdms_store.py
opendiamond/filter/__init__.py
opendiamond/filter/parameters.py
opendiamond/proxy/__init__.py
opendiamond/proxy/filter.py
opendiamond/proxy/search.py
opendiamond/proxy/utils.py
opendiamond/scopeserver/__init__.py
opendiamond/scopeserver/cocktail/__init__.py
opendiamond/scopeserver/cocktail/admin.py
opendiamond-10.1.1.dist-info/LICENSE
opendiamond-10.1.1.dist-info/METADATA
opendiamond-10.1.1.dist-info/WHEEL
opendiamond-10.1.1.dist-info/entry_points.txt
opendiamond-10.1.1.dist-info/top_level.txt
opendiamond-10.1.1.dist-info/RECORD
