Metadata-Version: 2.1
Name: opendiamond
Version: 10.1.1
Summary: OpenDiamond Platform for Interactive Search
Home-page: http://diamond.cs.cmu.edu/
Author: Carnegie Mellon University
Author-email: diamond@cs.cmu.edu
License: Eclipse Public License, Version 1.0
Platform: UNKNOWN
Classifier: License :: OSI Approved :: Eclipse Public License 1.0 (EPL-1.0)
Classifier: Programming Language :: Python :: 3
Requires-Dist: future (>=0.18.0)
Requires-Dist: lxml (>=3.2.1)
Requires-Dist: M2Crypto (>=0.21.1)
Requires-Dist: pip (>=1.5.6)
Requires-Dist: Pillow (>=6.2.0)
Requires-Dist: python-dateutil (>=1.5)
Requires-Dist: pyyaml (>=5.1.2)
Requires-Dist: six (>=1.9.0)
Provides-Extra: blaster
Requires-Dist: file-magic (>=0.3.0) ; extra == 'blaster'
Requires-Dist: pycurl (>=7.43.0) ; extra == 'blaster'
Requires-Dist: simplejson (>=3.10.0) ; extra == 'blaster'
Requires-Dist: sockjs-tornado (>=1.0.3) ; extra == 'blaster'
Requires-Dist: tornado (>=4.4.2) ; extra == 'blaster'
Requires-Dist: validictory (>=1.1.0) ; extra == 'blaster'
Provides-Extra: dataretriever
Requires-Dist: flask (>=0.12.4) ; extra == 'dataretriever'
Provides-Extra: diamondd
Requires-Dist: docker (>=3.7.0) ; extra == 'diamondd'
Requires-Dist: psutil (>=5.6.6) ; extra == 'diamondd'
Requires-Dist: PyYAML (>=4.2b1) ; extra == 'diamondd'
Requires-Dist: raven (>=6.6.0) ; extra == 'diamondd'
Requires-Dist: redis (>=2.10.3) ; extra == 'diamondd'
Requires-Dist: xmltodict (>=0.11.0) ; extra == 'diamondd'
Provides-Extra: scopeserver
Requires-Dist: Django (>=1.11.29) ; extra == 'scopeserver'
